setup.py
mcm/__init__.py
mcm/core.py
mcm/error.py
mcm/models.py
pymcm.egg-info/PKG-INFO
pymcm.egg-info/SOURCES.txt
pymcm.egg-info/dependency_links.txt
pymcm.egg-info/requires.txt
pymcm.egg-info/top_level.txt
pymcm.egg-info/zip-safe