Metadata-Version: 1.0
Name: pymcm
Version: 0.0.1
Summary: MagicCardMarket API client
Home-page: http://github.com/b3ni/pymcm
Author: Benito Rodriguez
Author-email: brarcos@gmail.com
License: MIT
Keywords: mcm
Platform: UNKNOWN
